desktop.ini
gamecord/__init__.py
gamecord/bot.py
gamecord/desktop.ini
gamecord/game.py
gamecord-0.0.9.dist-info/LICENSE
gamecord-0.0.9.dist-info/METADATA
gamecord-0.0.9.dist-info/WHEEL
gamecord-0.0.9.dist-info/desktop.ini
gamecord-0.0.9.dist-info/top_level.txt
gamecord-0.0.9.dist-info/RECORD
