Metadata-Version: 2.1
Name: gamecord
Version: 0.0.9
Summary: A helper framework for making games in Discord with discord.py.
Home-page: https://github.com/lanthony42/GameCord
Author: Anthony Louie
License: MIT
Download-URL: https://pypi.org/project/gamecord/
Keywords: Discord,discord.py
Platform: UNKNOWN
Requires-Dist: discord.py (>=1.5.0)
Requires-Dist: python-dotenv
